LICENSE.txt
MANIFEST.in
README.txt
setup.py
bin/ppmongo
ppmongo/__init__.py
ppmongo/actions.py
ppmongo/analyze.py
ppmongo/printing.py
ppmongo.egg-info/PKG-INFO
ppmongo.egg-info/SOURCES.txt
ppmongo.egg-info/dependency_links.txt
ppmongo.egg-info/requires.txt
ppmongo.egg-info/top_level.txt