Metadata-Version: 1.1
Name: ppmongo
Version: 0.1.2
Summary: Retrieve and pretty-print data from mongo
Home-page: https://github.com/anossov/ppmongo
Author: Pavel Anossov
Author-email: anossov@gmail.com
License: BSD
Platform: UNKNOWN
Classifier: Development Status :: 4 - Beta
Classifier: Programming Language :: Python :: 2.7
Classifier: Programming Language :: Python :: 3
Classifier: Environment :: Console
Classifier: Intended Audience :: Developers
Classifier: License :: OSI Approved :: BSD License
Classifier: Topic :: Utilities
Classifier: Topic :: Database
